profile_decorator/__init__.py
profile_decorator/profile_decorator.py
profile_decorator/report.py
profile_decorator-0.1.0.dist-info/WHEEL
profile_decorator-0.1.0.dist-info/METADATA
profile_decorator-0.1.0.dist-info/RECORD
