Metadata-Version: 2.1
Name: profile-decorator
Version: 0.1.0
Summary: A simple decorator to profile memory usage in production apps
Home-page: https://github.com/hkiang01/profile-decorator
License: MIT
Author: Harrison Kiang
Author-email: hkiang01@gmail.com
Maintainer: Harrison Kiang
Maintainer-email: hkiang01@gmail.com
Requires-Python: >=3.6.2,<4
Classifier: Intended Audience :: Information Technology
Classifier: License :: OSI Approved :: MIT License
Classifier: Natural Language :: English
Classifier: Operating System :: MacOS
Classifier: Operating System :: Microsoft :: Windows
Classifier: Operating System :: OS Independent
Classifier: Operating System :: POSIX :: Linux
Classifier: Operating System :: Unix
Classifier: Programming Language :: Python
Classifier: Programming Language :: Python :: 3
Classifier: Programming Language :: Python :: 3.6
Classifier: Programming Language :: Python :: 3.7
Classifier: Programming Language :: Python :: 3.8
Classifier: Programming Language :: Python :: 3.9
Classifier: Topic :: Software Development :: Build Tools
Classifier: Topic :: Software Development :: Debuggers
Classifier: Topic :: Software Development :: Libraries :: Python Modules
Requires-Dist: psutil (>=4.0.0)
